com/__init__.py
com/hayatapps/__init__.py
com/hayatapps/pa/__init__.py
com/hayatapps/pa/model/__init__.py
com/hayatapps/pa/model/paservice_pb2.py
com/hayatapps/pa/model/paservice_pb2.pyi
com/hayatapps/pa/model/paservice_pb2_grpc.py
com/hayatapps/pa/service/__init__.py
com/hayatapps/pa/service/paservice_service_pb2.py
com/hayatapps/pa/service/paservice_service_pb2.pyi
com/hayatapps/pa/service/paservice_service_pb2_grpc.py
com.hayatapps.pa.service.api-0.17.dist-info/LICENSE
com.hayatapps.pa.service.api-0.17.dist-info/METADATA
com.hayatapps.pa.service.api-0.17.dist-info/WHEEL
com.hayatapps.pa.service.api-0.17.dist-info/top_level.txt
com.hayatapps.pa.service.api-0.17.dist-info/RECORD
